bin/__init__.py
bin/main.py
cfgrep/__init__.py
cfgrep/cfgrep.py
cfgrep-1.0.5.dist-info/LICENSE
cfgrep-1.0.5.dist-info/METADATA
cfgrep-1.0.5.dist-info/NOTICE
cfgrep-1.0.5.dist-info/WHEEL
cfgrep-1.0.5.dist-info/entry_points.txt
cfgrep-1.0.5.dist-info/top_level.txt
cfgrep-1.0.5.dist-info/RECORD
