Metadata-Version: 2.1
Name: cfgrep
Version: 1.0.5
Summary: cfgrep is Cisco-like Config Context-aware Check grep
Home-page: https://github.com/tk-hayashi/cfgrep
Author: toshayas
Author-email: toshayas@cisco.com
License: UNKNOWN
Platform: UNKNOWN
Classifier: Programming Language :: Python :: 3.6
Classifier: License :: OSI Approved :: Apache Software License
Classifier: Operating System :: OS Independent
Requires-Dist: wheel
Requires-Dist: ciscoconfparse
Requires-Dist: netaddr
Requires-Dist: docopt
